ISCT/ISCT.py
ISCT/RandomProjection.py
ISCT/__init__.py
ISCT/datainpute.py
ISCT/splitmeasures.py
ISCT-0.1.2.dist-info/METADATA
ISCT-0.1.2.dist-info/WHEEL
ISCT-0.1.2.dist-info/top_level.txt
ISCT-0.1.2.dist-info/RECORD
