Metadata-Version: 2.2
Name: ISCT
Version: 0.1.2
Summary: Interpretable Sequence Clustering Tree
Author-email: Junjie Dong <jd445@qq.com>
Project-URL: Source, https://github.com/jd445/Interpretable-Sequence-Clustering-Tree
Project-URL: Issues, https://github.com/jd445/Interpretable-Sequence-Clustering-Tree/issues
Keywords: ISCT,sequence,clustering,tree
Classifier: Programming Language :: Python :: 3
Classifier: License :: OSI Approved :: MIT License
Classifier: Operating System :: OS Independent
Requires-Dist: numpy<2
Requires-Dist: pandas>=2.0.1
Requires-Dist: scikit-learn>=1.2.2
Requires-Dist: prefixspan>=0.5.2
Requires-Dist: graphviz>=0.20.3
